customer_analysis.py
customer_analysis_annyandr-1.0.dist-info/METADATA
customer_analysis_annyandr-1.0.dist-info/WHEEL
customer_analysis_annyandr-1.0.dist-info/entry_points.txt
customer_analysis_annyandr-1.0.dist-info/top_level.txt
customer_analysis_annyandr-1.0.dist-info/RECORD
